vaaibody/__init__.py
vaaibody/audio_gest_player.py
vaaibody/bvh_viewer.py
vaaibody/decompressor.py
vaaibody/decompressor_savedb.py
vaaibody/decompressor_train.py
vaaibody/decompressor_util.py
vaaibody/dump_test.py
vaaibody/main.py
vaaibody/main_nn.py
vaaibody/core/__init__.py
vaaibody/core/audio.py
vaaibody/core/blending.py
vaaibody/core/database.py
vaaibody/core/feature.py
vaaibody/core/filter_frame.py
vaaibody/core/frame.py
vaaibody/core/gesture_matching.py
vaaibody/core/modAudio.py
vaaibody/core/motion.py
vaaibody/core/skeleton.py
vaaibody/module/__init__.py
vaaibody/module/idle_module.py
vaaibody/module/nontalking_control_module.py
vaaibody/module/tag_processing_module.py
vaaibody/module/transition_module.py
vaaibody/parameter/__init__.py
vaaibody/parameter/gesture_matching_parameter.py
vaaibody/utilities/__init__.py
vaaibody/utilities/audio_motion_synch.py
vaaibody/utilities/audio_utils.py
vaaibody/utilities/blending_utils.py
vaaibody/utilities/exporter.py
vaaibody/utilities/filter.py
vaaibody/utilities/frame_utils.py
vaaibody/utilities/motion_var_utils.py
vaaibody/utilities/quat.py
vaaibody/utilities/rendering_utils.py
vaaibody/utilities/timechecker.py
vaaibody/utilities/txform.py
vaaibody/utilities/utils.py
vaaibody/viewer/__init__.py
vaaibody/viewer/camera.py
vaaibody/viewer/controller.py
vaaibody/viewer/double_bvh_viewer.py
vaaibody/viewer/gesture_result_viewer.py
vaaibody/viewer/gui_viewer.py
vaaibody/viewer/handler.py
vaaibody/viewer/item_data.py
vaaibody/viewer/item_drawer.py
vaaibody/viewer/obj_loader.py
vaaibody-0.0.1.dist-info/METADATA
vaaibody-0.0.1.dist-info/WHEEL
vaaibody-0.0.1.dist-info/top_level.txt
vaaibody-0.0.1.dist-info/RECORD
