Metadata-Version: 2.1
Name: vaaibody
Version: 0.0.1
Summary: VAAI-BODY gesture generation module
Author: yoonhee
Author-email: yhkim@ncsoft.com
Requires-Python: >=3.8
Requires-Dist: numpy (==1.23.4)
Requires-Dist: scipy (==1.9.2)
